{"version":1,"resource":"file:///d%3A/code/VUE3-BASICS/index1b.html","entries":[{"id":"QePm.html","timestamp":1668739622361},{"id":"ycyk.html","timestamp":1668740310783},{"id":"VJhd.html","timestamp":1668740417508},{"id":"oHMs.html","timestamp":1668740520896},{"id":"1Igk.html","timestamp":1668740630339},{"id":"Wvl3.html","source":"undoRedo.source","timestamp":1668741012046},{"id":"7DmQ.html","source":"undoRedo.source","timestamp":1668741058198},{"id":"pdX6.html","timestamp":1668741075263},{"id":"EX2r.html","source":"undoRedo.source","timestamp":1668741222857},{"id":"TgTT.html","timestamp":1668741336565},{"id":"4Pgk.html","timestamp":1668741379899},{"id":"4nUg.html","timestamp":1668741827161},{"id":"f1RW.html","timestamp":1668741863717},{"id":"Hz6z.html","timestamp":1668741955634},{"id":"9xqY.html","timestamp":1668742008288},{"id":"CQix.html","timestamp":1668742339484},{"id":"2ors.html","source":"undoRedo.source","timestamp":1668742384893},{"id":"aFk4.html","source":"undoRedo.source","timestamp":1668742399076},{"id":"Blkt.html","source":"undoRedo.source","timestamp":1668742429871},{"id":"X481.html","source":"renamed.source","timestamp":1668742559740}]}